<?xml version="1.0" encoding="utf-8"?>
<data>
  <table name="POAddress">
    <col name="CompanyID" type="Int" default="Zero" />
    <col name="AddressID" type="Int" identity="true" />
    <col name="BAccountID" type="Int" />
    <col name="RevisionID" type="Int" />
    <col name="IsDefaultAddress" type="Bit" />
    <col name="AddressLine1" type="NVarChar(50)" nullable="true" />
    <col name="AddressLine2" type="NVarChar(50)" nullable="true" />
    <col name="AddressLine3" type="NVarChar(50)" nullable="true" />
    <col name="City" type="NVarChar(50)" nullable="true" />
    <col name="CountryID" type="NVarChar(2)" nullable="true" />
    <col name="State" type="NVarChar(50)" nullable="true" />
    <col name="PostalCode" type="VarChar(20)" nullable="true" />
    <col name="IsValidated" type="Bit" />
    <col name="PseudonymizationStatus" type="Int" nullable="true" default="Zero" />
    <col name="NoteID" type="UniqueIdentifier" />
    <col name="CreatedByID" type="UniqueIdentifier" />
    <col name="CreatedByScreenID" type="Char(8)" />
    <col name="CreatedDateTime" type="DateTime" />
    <col name="LastModifiedByID" type="UniqueIdentifier" />
    <col name="LastModifiedByScreenID" type="Char(8)" />
    <col name="LastModifiedDateTime" type="DateTime" />
    <col name="tstamp" type="Timestamp" />
    <col name="BAccountAddressID" type="Int" nullable="true" />
  </table>
  <rows>
    <row AddressID="3" BAccountID="5532" RevisionID="1" IsDefaultAddress="1" AddressLine1="777 West 21st St." City="New York" CountryID="US" State="NY" IsValidated="0" PseudonymizationStatus="0" NoteID="1cb3fa0f-96d8-4c6e-b477-022d943f6dbe" CreatedByID="b5344897-037e-4d58-b5c3-1bdfd0f47bf9" CreatedByScreenID="PO301000" LastModifiedByID="b5344897-037e-4d58-b5c3-1bdfd0f47bf9" LastModifiedByScreenID="PO301000" BAccountAddressID="5850" />
    <row AddressID="4" BAccountID="5624" RevisionID="1" IsDefaultAddress="1" CountryID="US" IsValidated="0" PseudonymizationStatus="0" NoteID="d04e6d67-c447-4d9e-bf86-d6fc329ee16b" CreatedByID="b5344897-037e-4d58-b5c3-1bdfd0f47bf9" CreatedByScreenID="PO301000" LastModifiedByID="b5344897-037e-4d58-b5c3-1bdfd0f47bf9" LastModifiedByScreenID="PO301000" BAccountAddressID="5942" />
    <row AddressID="1168" BAccountID="5538" RevisionID="2" IsDefaultAddress="1" AddressLine1="205 West St" City="Sausalito" CountryID="US" State="CA" PostalCode="94965-2322" IsValidated="0" PseudonymizationStatus="0" NoteID="f3106715-38d3-49cf-a566-41a787fae1cf" CreatedByID="b5344897-037e-4d58-b5c3-1bdfd0f47bf9" CreatedByScreenID="PO301000" LastModifiedByID="b5344897-037e-4d58-b5c3-1bdfd0f47bf9" LastModifiedByScreenID="PO301000" BAccountAddressID="5856" />
    <row AddressID="1169" BAccountID="5437" RevisionID="4" IsDefaultAddress="1" AddressLine1="1000 5th Ave" City="New York" CountryID="US" State="NY" PostalCode="10028-0113" IsValidated="0" PseudonymizationStatus="0" NoteID="89d7aba2-1152-4908-9a8e-642e4cbe595c" CreatedByID="b5344897-037e-4d58-b5c3-1bdfd0f47bf9" CreatedByScreenID="PO301000" LastModifiedByID="b5344897-037e-4d58-b5c3-1bdfd0f47bf9" LastModifiedByScreenID="PO301000" BAccountAddressID="5755" />
  </rows>
</data>