<?xml version="1.0" encoding="utf-8"?>
<data>
	<table name="DrawingLogStatus">
		<col name="CompanyID" type="Int" default="Zero" />
		<col name="CompanyDrawingLogStatusId" type="Int" identity="true" />
		<col name="Name" type="NVarChar(255)" />
		<col name="IsDefault" type="Bit" nullable="true" />
		<col name="Description" type="NVarChar(255)" nullable="true" />
		<col name="DrawingLogStatusId" type="Int" default="IdentCurrent" />
		<col name="CompanyMask" type="VarBinary(32)" default="CompanyMaskReadOnly" />
	</table>
	<rows>
		<row CompanyDrawingLogStatusId="1" Name="N/A" IsDefault="1" Description="DEFAULT" DrawingLogStatusId="100000" />
	</rows>
</data>