<?xml version="1.0" encoding="utf-8"?>
<data>
	<table name="ImageRecognitionModelField">
		<col name="CompanyID" type="Int" default="Zero" />
		<col name="ModelID" type="Int" />
		<col name="FieldName" type="NVarChar(255)" />
		<col name="FieldType" type="NVarChar(255)" />
		<col name="IsVirtual" type="Bit" />
		<col name="CompanyMask" type="VarBinary(32)" default="CompanyMaskReadOnly" />
	</table>
	<rows>
		<row ModelID="1" FieldName="ExpenseCategory" FieldType="Text" IsVirtual="1" />
		<row ModelID="1" FieldName="MerchantAddress" FieldType="Text" IsVirtual="0" />
		<row ModelID="1" FieldName="MerchantName" FieldType="Text" IsVirtual="0" />
		<row ModelID="1" FieldName="MerchantPhoneNumber" FieldType="Text" IsVirtual="0" />
		<row ModelID="1" FieldName="Subtotal" FieldType="Number" IsVirtual="0" />
		<row ModelID="1" FieldName="Tax" FieldType="Number" IsVirtual="0" />
		<row ModelID="1" FieldName="Total" FieldType="Number" IsVirtual="0" />
		<row ModelID="1" FieldName="TransactionDate" FieldType="Date" IsVirtual="0" />
		<row ModelID="1" FieldName="TransactionTime" FieldType="Time" IsVirtual="0" />
	</rows>
</data>