<?xml version="1.0" encoding="utf-8"?>
<data>
  <table name="AUSchedule">
    <col name="CompanyID" type="Int" default="Zero" />
    <col name="ScreenID" type="Char(8)" />
    <col name="ScheduleID" type="Int" default="IdentCurrent" />
    <col name="CompanyScheduleID" type="Int" identity="true" />
    <col name="Description" type="NVarChar(128)" />
    <col name="GraphName" type="VarChar(128)" />
    <col name="ViewName" type="VarChar(128)" />
    <col name="FilterName" type="VarChar(128)" nullable="true" />
    <col name="TableName" type="VarChar(128)" />
    <col name="BranchID" type="Int" nullable="true" />
    <col name="FilterCntr" type="SmallInt" />
    <col name="FillCntr" type="SmallInt" />
    <col name="IsActive" type="Bit" />
    <col name="ActionName" type="VarChar(128)" />
    <col name="TimeZoneID" type="VarChar(32)" />
    <col name="ScheduleType" type="Char(1)" />
    <col name="DailyFrequency" type="SmallInt" />
    <col name="WeeklyFrequency" type="SmallInt" />
    <col name="WeeklyOnDay1" type="Bit" />
    <col name="WeeklyOnDay2" type="Bit" />
    <col name="WeeklyOnDay3" type="Bit" />
    <col name="WeeklyOnDay4" type="Bit" />
    <col name="WeeklyOnDay5" type="Bit" />
    <col name="WeeklyOnDay6" type="Bit" />
    <col name="WeeklyOnDay7" type="Bit" />
    <col name="MonthlyFrequency" type="SmallInt" />
    <col name="MonthlyDaySel" type="Char(1)" />
    <col name="MonthlyOnDay" type="SmallInt" />
    <col name="MonthlyOnWeek" type="SmallInt" />
    <col name="MonthlyOnDayOfWeek" type="SmallInt" />
    <col name="PeriodFrequency" type="SmallInt" />
    <col name="PeriodDateSel" type="Char(1)" />
    <col name="PeriodFixedDay" type="SmallInt" />
    <col name="StartDate" type="SmallDateTime" />
    <col name="NoEndDate" type="Bit" />
    <col name="EndDate" type="SmallDateTime" nullable="true" />
    <col name="NoRunLimit" type="Bit" />
    <col name="RunLimit" type="SmallInt" nullable="true" />
    <col name="RunCntr" type="Int" />
    <col name="NextRunDate" type="SmallDateTime" />
    <col name="LastRunDate" type="SmallDateTime" nullable="true" />
    <col name="LastRunErrorLevel" type="SmallInt" />
    <col name="LastRunResult" type="NVarChar(MAX)" nullable="true" />
    <col name="StartTime" type="SmallDateTime" nullable="true" />
    <col name="EndTime" type="SmallDateTime" nullable="true" />
    <col name="Interval" type="SmallInt" />
    <col name="NextRunTime" type="SmallDateTime" />
    <col name="TemplateScreenID" type="Char(8)" nullable="true" />
    <col name="ExactTime" type="Bit" default="Zero" />
    <col name="CreatedByID" type="UniqueIdentifier" />
    <col name="CreatedByScreenID" type="Char(8)" />
    <col name="CreatedDateTime" type="DateTime" />
    <col name="LastModifiedByID" type="UniqueIdentifier" />
    <col name="LastModifiedByScreenID" type="Char(8)" />
    <col name="LastModifiedDateTime" type="DateTime" />
    <col name="tstamp" type="Timestamp" />
    <col name="DeletedDatabaseRecord" type="Bit" default="Zero" />
    <col name="CompanyMask" type="VarBinary(32)" default="CompanyMaskReadOnly" />
    <col name="NoteID" type="UniqueIdentifier" />
    <col name="HistoryRetainCount" type="SmallInt" nullable="true" />
    <col name="KeepFullHistory" type="Bit" default="Zero" />
  </table>
  <rows>
    <row ScreenID="FS501200" ScheduleID="148" CompanyScheduleID="148" Description="Update Service Contracts Status" GraphName="PX.Objects.FS.ServiceContractStatusProcess" ViewName="ServiceContracts" FilterName="Filter" TableName="PX.Objects.FS.FSServiceContract" FilterCntr="0" FillCntr="0" IsActive="0" ActionName="ProcessAll" TimeZoneID="GMTE0000U" ScheduleType="D" DailyFrequency="1" WeeklyFrequency="1" WeeklyOnDay1="1" WeeklyOnDay2="0" WeeklyOnDay3="0" WeeklyOnDay4="0" WeeklyOnDay5="0" WeeklyOnDay6="0" WeeklyOnDay7="0" MonthlyFrequency="1" MonthlyDaySel="D" MonthlyOnDay="1" MonthlyOnWeek="1" MonthlyOnDayOfWeek="1" PeriodFrequency="1" PeriodDateSel="S" PeriodFixedDay="1" StartDate="2017-11-24 00:00:00" NoEndDate="1" NoRunLimit="1" RunCntr="1" NextRunDate="2017-11-26 00:00:00" LastRunDate="2017-11-25 00:00:00" LastRunErrorLevel="0" LastRunResult="The operation has been completed successfully." Interval="0" NextRunTime="1900-01-01 00:00:00" ExactTime="1" CreatedByID="b5344897-037e-4d58-b5c3-1bdfd0f47bf9" CreatedByScreenID="FS501200" LastModifiedByID="b5344897-037e-4d58-b5c3-1bdfd0f47bf9" LastModifiedByScreenID="SM205020" DeletedDatabaseRecord="0" NoteID="699b3334-37d1-e711-8588-484520427b37" HistoryRetainCount="1" KeepFullHistory="0" />
    <row ScreenID="ML501000" ScheduleID="100000" CompanyScheduleID="153" Description="Process Machine Learning Events" GraphName="PX.ML.UI.Graphs.MLTrainer" ViewName="Jobs" TableName="PX.ML.UI.Graphs.MLTrainer+MLEventGroup" FilterCntr="0" FillCntr="0" IsActive="1" ActionName="ProcessAll" TimeZoneID="GMTE0000U" ScheduleType="D" DailyFrequency="1" WeeklyFrequency="1" WeeklyOnDay1="1" WeeklyOnDay2="0" WeeklyOnDay3="0" WeeklyOnDay4="0" WeeklyOnDay5="0" WeeklyOnDay6="0" WeeklyOnDay7="0" MonthlyFrequency="1" MonthlyDaySel="D" MonthlyOnDay="1" MonthlyOnWeek="1" MonthlyOnDayOfWeek="1" PeriodFrequency="1" PeriodDateSel="S" PeriodFixedDay="1" StartDate="2018-12-10 00:00:00" NoEndDate="1" NoRunLimit="1" RunCntr="0" NextRunDate="2018-12-10 00:00:00" LastRunErrorLevel="0" StartTime="1900-01-01 01:00:00" Interval="0" NextRunTime="1900-01-01 01:00:00" ExactTime="0" CreatedByID="b5344897-037e-4d58-b5c3-1bdfd0f47bf9" CreatedByScreenID="ML501000" LastModifiedByID="b5344897-037e-4d58-b5c3-1bdfd0f47bf9" LastModifiedByScreenID="ML501000" DeletedDatabaseRecord="0" NoteID="dd0a04e9-7efc-e811-ad62-0028f884a1a6" HistoryRetainCount="1" KeepFullHistory="0" />
    <row ScreenID="SM507010" ScheduleID="7" CompanyScheduleID="7" Description="Send/Receive Emails" GraphName="PX.SM.EmailSendReceiveMaint" ViewName="FilteredItems" FilterName="Filter" TableName="PX.SM.EMailAccount" FilterCntr="0" FillCntr="0" IsActive="1" ActionName="ProcessAll" TimeZoneID="GMTE0000U" ScheduleType="D" DailyFrequency="1" WeeklyFrequency="1" WeeklyOnDay1="1" WeeklyOnDay2="0" WeeklyOnDay3="0" WeeklyOnDay4="0" WeeklyOnDay5="0" WeeklyOnDay6="0" WeeklyOnDay7="0" MonthlyFrequency="1" MonthlyDaySel="D" MonthlyOnDay="1" MonthlyOnWeek="1" MonthlyOnDayOfWeek="1" PeriodFrequency="1" PeriodDateSel="S" PeriodFixedDay="1" StartDate="2013-03-19 00:00:00" NoEndDate="1" NoRunLimit="1" RunCntr="5" NextRunDate="2016-12-05 00:00:00" LastRunDate="2016-12-05 07:30:00" LastRunErrorLevel="0" LastRunResult="The operation has been completed successfully." Interval="5" NextRunTime="1900-01-01 07:35:00" ExactTime="0" CreatedByID="b5344897-037e-4d58-b5c3-1bdfd0f47bf9" CreatedByScreenID="SM507010" LastModifiedByID="b5344897-037e-4d58-b5c3-1bdfd0f47bf9" LastModifiedByScreenID="SM507010" DeletedDatabaseRecord="0" NoteID="0e331f93-3104-4ea3-a32b-aec5a220493b" HistoryRetainCount="1" KeepFullHistory="0" />
  </rows>
</data>